image_tiles/__init__.py
image_tiles/file_exists.py
image_tiles/file_exists_test.py
image_tiles/glob.py
image_tiles/glob_test.py
image_tiles/image.py
image_tiles/image_test.py
image_tiles/image_tiles_server.py
image_tiles/normalization.py
image_tiles/normalization_test.py
image_tiles/static/main.css
image_tiles/static/main.js
image_tiles/static/normalize.css
image_tiles/static/sakura.css
image_tiles/templates/image_tiles.html
image_tiles-0.1.5.dist-info/METADATA
image_tiles-0.1.5.dist-info/WHEEL
image_tiles-0.1.5.dist-info/entry_points.txt
image_tiles-0.1.5.dist-info/licenses/LICENSE
image_tiles-0.1.5.dist-info/RECORD
