Metadata-Version: 2.4
Name: image_tiles
Version: 0.1.5
Summary: Serve a webpage with images from a folder.
Project-URL: Homepage, https://github.com/moonshinelabs/image_tiles
Author-email: Nate Harada <image_tiles@moonshinelabs.ai>
License: MIT
License-File: LICENSE
Keywords: image,tiles,visualize
Classifier: License :: OSI Approved :: MIT License
Classifier: Programming Language :: Python :: 3
Requires-Python: >=3.12
Requires-Dist: flask==3.0.2
Requires-Dist: imageio==2.24.0
Requires-Dist: loguru==0.6.0
Requires-Dist: numpy>=1.26.0
Requires-Dist: smart-open==6.3.0
Requires-Dist: tifffile==2022.10.10
Provides-Extra: all
Requires-Dist: boto3>=1.26.54; extra == 'all'
Requires-Dist: google-cloud-storage>=2.0.0; extra == 'all'
Provides-Extra: aws
Requires-Dist: boto3>=1.26.54; extra == 'aws'
Provides-Extra: gcp
Requires-Dist: google-cloud-storage>=2.0.0; extra == 'gcp'
